m5meta.py
m5meta-1.0.4.dist-info/LICENSE
m5meta-1.0.4.dist-info/METADATA
m5meta-1.0.4.dist-info/WHEEL
m5meta-1.0.4.dist-info/top_level.txt
m5meta-1.0.4.dist-info/RECORD
